[
  {
    "id": 1,
    "title": "Level up",
    "media": "https://youtu.be/KzAvc9QWjV0?si=rMqBwEV8z2Or3vZR",
    "type": "Amv"
  },
  {
    "id": 2,
    "title": "Masa depan mu",
    "media": "https://youtu.be/8KVa3O9or6Y?si=-jl4xNq0N5C_vyq1",
    "type": "Amv"
  },
  {
    "id": 3,
    "title": "3D Modern Minimalis House",
    "media": "https://youtu.be/kHuufscO_-M?si=xto8iAgNA8UaSJHG",
    "type": "3d"
  },
  {
    "id": 4,
    "title": "End of Beginning",
    "media": "https://youtu.be/WGvtliE1298?si=u_rT4GEr43IksWPs",
    "type": "Amv"
  },
  {
    "id": 5,
    "title": "Shut Up and Dance",
    "media": "https://youtu.be/rFiSI1SUjjg?si=SIluS7uvt9khQwEX",
    "type": "Amv"
  },
  {
    "id": 6,
    "title": "3D Cinematic",
    "media": "https://youtu.be/GVJuvleJasA?si=IWxaNvB3npZ-u_ht",
    "type": "3d"
  },
  {
    "id": 7,
    "title": "Elaina Jedag-Jedug",
    "media": "https://youtu.be/jtybWGVeUwA?si=Z9sXkCAaMPZK2NnM",
    "type": "Jj"
  },
  {
    "id": 8,
    "title": "Background Overlay Streaming",
    "media": "https://drive.google.com/file/d/1qEEnC8ipNNsbsp_vJUYgAUsD13x7Zicb/view?usp=drive_link",
    "type": "Overlay"
  },
  {
    "id": 9,
    "title": "Highlight Streaming Overlay",
    "media": "https://drive.google.com/file/d/1YbfBMvZAxPBLNMAuseZD6QDIB4S7kdEJ/view?usp=sharing",
    "type": "Overlay"
  },
  {
    "id": 10,
    "title": "Rewrite the Stars",
    "media": "https://youtu.be/sm1N-9D4qL0?si=nmyCAoxqjCLK6JC7",
    "type": "Amv"
  },
  {
    "id": 11,
    "title": "Animation JJ MLBB",
    "media": "https://drive.google.com/file/d/1S5Vw6w98b39eDq6tNWYmONbcJeZ9Pw3H/view?usp=sharing",
    "type": "3d"
  },
  {
    "id": 12,
    "title": "3D Animation Kutukan Mantan",
    "media": "https://drive.google.com/file/d/1hGyLDBg55WWkaALEhf8PyGgkadxmXjZG/view?usp=drivesdk",
    "type": "3d"
  },
  {
    "id": 13,
    "title": "Mograph Intro Farewell Eterious",
    "media": "https://drive.google.com/file/d/1-fUZdyo5NuzDiNKb7EtofJmF06bhwc6e/view?usp=drivesdk",
    "type": "Overlay"
  },
  {
    "id": 14,
    "title": "Membership Promotion",
    "media": "https://drive.google.com/file/d/13V3pi312NDsZl866KhMhQGmz7gul79qG/view?usp=drivesdk",
    "type": "Overlay"
  },
  {
    "id": 15,
    "title": "Jedag Jedug Special 100k Like",
    "media": "https://drive.google.com/file/d/1SMuSpWtePKdxpH7-btxmq9_ZMy0dpsZ9/view?usp=drivesdk",
    "type": "Jj"
  },
  {
    "id": 16,
    "title": "Jedag Jedug Golden Let's Party",
    "media": "https://drive.google.com/file/d/1EUbwSUkG3pvCur_fzvDKlTUUdEwSsMSH/view?usp=drivesdk",
    "type": "Jj"
  }
]
